{"type":"FeatureCollection","features":[{"type":"Feature","geometry":{"coordinates":[4.306641,51.165567],"type":"Point"},"properties":{"name":"un punto","description":"blabla"},"id":"5oJho"}],"_umap_options":{"displayOnLoad":true,"inCaption":true,"browsable":true,"editMode":"advanced","name":"Capa 1","id":"609c80cc-073b-4760-b4f6-010aa74d4082","rank":0,"remoteData":{},"fields":[{"key":"name","type":"String"},{"key":"description","type":"Text"}]}}